{"current":{"season":1,"year":2025,"formatsGeneratedAt":2025,"period":4},"formatSchedule":{"1":["randombattle","ou","ubers","lc","pu","doublesou"],"2":["randombattle","ou","nu","monotype","doublesou","uu"],"3":["randombattle","ou","ubers","ru","nu","uu"],"4":["randombattle","ou","ru","monotype","lc","pu"]},"badgeholders":{"1":{"gen9randombattle":{"gold":["michaelderbeste2","norman2","70to90gxe"],"silver":["pokeblade101","assidion","james","ladywriter","xyki","starwheel","justhaxrelax","jb291","haunterboy28","lizardune","sirtetris","vitoran","helicopyer","arabbit","togawajun","prodigezz","pocketfan25","jyusaan","portobellomushroom","pkvpokevin","danbear02","mmo00","kukpoo","ltalt1","toiletsmell","frankrayquaza","astinov"],"bronze":["mylifeisdance","amyisraelchailatte","hammy358","flightsoffantsy","wintersim","mk7all","langwuyao","nitehartssd","node","aguni274","shiniu2","duck","thearsenal1886","milkreo","sothreatening","whoistosay","megaketsuban","stareal","honghoornstaart","hitoribocchidesu","galak0","basebear","peekomino","chiefbeef1234","jornlande","articoo","freezai","fatmarmot","teslaspacex","ok132","fdjskl","piyush21","smokyaim","belebepoke","turtles88","phantasmiccat","thedudeblake","vazquez20","dg9kbw","nooksngrannies","referrals","zap","tobiaxy","nolttt092","betathunder","sowla","chemcoop","countingworms","ventish12","therandomanno","gokupichu","ryonabot","murongjin","cansermaro8","rambiedrascal","kasslekouy","dwagone","michielleus","yukisukimax","freyaknightvgc","bryanevangelista","chogger420","sebeck","bigbaz","sigurdzz","sleepygen9","octooooppus","gothampaladin","koffingwoffing","xox11108"]},"gen9ou":{"gold":["switchbladess","relicstone","c0ldsn0w"],"silver":["nagol40spaz","srfcearea","fsstk2p46","dgymteacher","ctannn","hoonlybitch","lynx1240","ajonymousnon","peakiechu","vouv","psykadelicswitch","drawyoursword","glowingsnow","stariaki","soccerfan123","rjyoip","nolimitholdem","cloudyej","oblivions1","goreshyt","143forever","jb291","asoulforasoul","rawmightjust","dlc23","faronaan","sirpeanutcronch"],"bronze":["chusei20","inertialinitiative","gremlins34","notveryzowwy","clrcusmaximus","lt124yhxebec","alostslaking","ajellyfish","troublewillfindme","twomoreforyall","prav33n","forever1507","suprya","lt123vb87","ezws","rockwalrus","belialking","noob1877test","butterycrap","weavilesucks930","lightsv","wanesa","losts0ulsmc","yoyolord","husali","alexander90281","o12d","yfleshcatchy","enemaaddict","ithrow24","jeandonis02","oughbliss","thedragongates","dongfanbubai","hzf","onthewavenow","poobadooba","iznamakin","nica4444","porygonfan1","jiuyuansit","nyamawemba","sommeliersam","uhhhhhhhhhhh1","1800main","anonymousjon","goatimm0rtal","abuzittin","owariowari","chaoticcrashout","starwarsfan95","54insanerats","levelssi","backkartana","lzc123456","lightdn","hoopaunshowered","jefo","pokemoninvestor","depakine","healorant","greppistafanclub","sfinctinatih","pudistorblack","learninggen9ou","tokiwakano","chungusoflif","amphibiansriseup","ougpkevingates","hellooomonster"]},"gen9ru":{"gold":["hjkhj","naturesconqueror","mannymanfred"],"silver":["stalldemoney","hoopsspooh","ohimember","bigoldru","canardaltrr","bonobo880","notgoodenuff","lamiellerie","bigolddaniolo7","auragbego","flaigomenjoyer","baiheyueai","ibeonladder","daharan0","pepeduce","nutimnuts","zephyyyr","sirfresh","flashpaparazzi","akaoma","prontoloco","lime","skyltie","billieisfat","jrwy","dognationwooo","mamovsthegeneric"],"bronze":["mamoisfat","hakkenenclaquette","urcadurfly","gumbopop","papichef","lappytop","canardmotr2","rezeishot","changeofapenny","somepepper","stallinru","dopelgaanger","theleavesdance","toraflora","dklhs","redoinem","krombacherspezi3","sitinho6","panoramafiesta","canardj1t2","dcae3","s4sh","feldspathforthewin","misseisbroken","askov","princesseetoile","dutchum","gengarsdestiny","rult74kkits","jaylek","stanleygarden","knockdowncenter","salmuerasetenta","m3p0","bananas12op","soulking0","roaringmoonlight2","ruokmommy","drm3","newmax","paradimensionality","rainrush","hoodraenjoyer","dumteszter","beelamp","rentschler","savesalamence2","thanksdocter","sheglows98","crchrm","rult85dahareng","quelana","svruladder","kolibri","alligatocosaimass","daidaiwo","rabidkobold","akdban","tettey","jonbilbaobi","notclevergugu","blazingcloud","kingswit","kwayvo","kotanagrelha","titiechecs","malktyme","drop6nukers","rult50dhareng","assab"]},"gen9monotype":{"gold":["dieuamphibien","ltranc","ceeuu2"],"silver":["weedlenium","naturesconqueror","hoonlybitch","sawsc","trainingig","aaaaassgaming","ironmichael66","oregongirls","palonet0","aaaaahowdogamework","mteverestsherpa","criminalesetoso","xyz","bigolddaniolo7","auvergneorigine","rainbowchrome","christmaskisses","jessyboris2712","teragranbull","kitealuluuu","edsheerangaming","mattandmello2","darkshowl","inanickoftime","granularity","khahara","louisaalcott"],"bronze":["sparrowsgrace","alabamagirls","londig","crashy","scarfire","cptkraken","ceeoo","ahnqirajconqueror","aaaaalt2","mshrshowl","lapindeschiottes","rightwhereuleftmii","washyourgrapes","rindaokami","filiaalice96","caffeinatedgengar","no1khaharahater","cienflores","freearcrock","spitfirearcanine","stads","imperiosus","friendwithin","whitespaniard","baaaaadges","ltrancbadgesig","youwillgivemeanegg","hammy358","jackuzzing","lilgodd","azick","ryasnek","grapenostalgia","tagualalabacela","nacht556","mralexnui","smilingturtoise","themiwawa","unaware7","ylove8","lindomar","improbableblob","pengairxan","tufftuf","serenegraceabuser","dayhealer","unchained3","nikkidoll","vodoom","user32463","kiteatest","shaomao","jollytogekiss","thatisagreatgrape","pannawit12235","chyair","londib","mastophobia","thewyvernking","thiccsola","kibgangster","justhk","annihilapebroken","pugzig9","railu","gumgumdawngatling","soma","st4rfl1tt14","coo1313","frol1"]},"gen9lc":{"gold":["turtwigtothetop","suwayriafelc","greedyeb"],"silver":["eniigma","hylianprodigy","wintertorm","kisx","fireshell","eodas","cowknuts","winterbub","mimology","cometlilim","turtwigmygoat","sodatshowderp","sceptember","stupidflou","xonks","bmatlb017am","xiaobaima","ohhaewon","revoltedwaves","buckdancer","juanwilkesbot","lavishkj","borntomorrow","witchingqueen","jocalsarereal","juanwilkesbooth","sitrisnerd"],"bronze":["indyana","zijianzhou","buckdancersmurf","seansu","poopoostinkybutt","maiarua","drinkurprunejuice","acehunter8","bmatlb01fireshell","lcwcfiller","kisssheep","xzeroxman","brotherklaus","mienfozinha","cinnamonsunset","larvonat","tobiaszek","chubbyhippo","lokifanfanclub","hutzell","thetobby","rarre","torchic2cheap","bmatb01starshoping","popularhamster","prollythegoat","kurisutoforo","jznvt","guysbeforefrys","invitro55","daiwascarlett","fakenails","sailormoan","averagelcenjoyer","sungchipwoo","jenniferfang","stunfisknipe","realemmanuel","half0dds","taiilsx","bmatlb01merlin","fille","snowderp","thegreatdemon","ptkmoekyuun","ambipongus","adsadc9","crabmanjohnson","exguardian","sunoutgunsout","aacro","netskinate","elfuseon","gregoreturns","jrwy","roypopolocroix","whscsh","touhoukhoa","fate1q","melonnolem","ericversus","humperdumper","derpderpity925","mmtaccos","impeniigma","adsax","spongeon","adasax","lukas768","washedreal"]},"gen9pu":{"gold":["wintertorm","nomore09rain","sayinghello"],"silver":["alcazz","ffszer","pepeopponent","ghostthreads","imonlyhere4daparty","gghht","destinybond5","hogridaah","raphalcaz","c0ngratulati0ns","ologramoghosto","canttouchmydream","platum2","koperutade","remnonb","dddreveal","cantseeyoureyes","lum1seterne","platum","bonobo880","rhydondeetznuts","panoramafiesta","miloticrit","toraflora","krillinenjoyer","zoowi","buzbee2000"],"bronze":["trainerluther","bottomhax","emremor9","drdof","roaringmoonlight2","rotomfanno1","dirkmot","error404notfoundr","evillana","astrazyderia","dirkrot","senzotanaka","pult1mgblsh","fuzzbox","bayleave","wrapmoosic","houbinyu","yimnotsuzuka","platumyplatumay","tatata1","yassyslay","goldenbough","derbeste5","ahseeflay","livarupp","davidhe96","gabbianocorso","bathtubhippo","spikeoverflow","efferfezant","digsbykid","endlessdark9","bellalala","thebhoy","flymeupsohigh","classyslay","scarfkricketune","soulisdew","crappyplay","hoot1","femboyxl","avanimals","amoebasaucers","menfhis","lailai333","greenmachine","hoesinhoenn","4everendeavor","saveththeday","keotest","amoongussinpu","standardice","rioverde12","davidsdilemma","bringbackreturn","dracopope","lush","pwnch","heracrossinpu","usnegoated","dirkvader","stillinluv","four11","foliedesyaourts","dirktales","endofrenoir","caramelribbon","wtfisthis6","carbocounting","toxicmob"]}}}}